obniz/__init__.py
obniz/obniz/__init__.py
obniz/obniz/__version__.py
obniz/obniz/obniz_components.py
obniz/obniz/obniz_connection.py
obniz/obniz/obniz_parts.py
obniz/obniz/obniz_system_methods.py
obniz/obniz/obniz_uis.py
obniz/obniz/libs/__init__.py
obniz/obniz/libs/embeds/__init__.py
obniz/obniz/libs/embeds/display.py
obniz/obniz/libs/embeds/switch.py
obniz/obniz/libs/embeds/ble/__init__.py
obniz/obniz/libs/embeds/ble/ble.py
obniz/obniz/libs/embeds/ble/ble_advertisement.py
obniz/obniz/libs/embeds/ble/ble_advertisement_builder.py
obniz/obniz/libs/embeds/ble/ble_attribute_abstract.py
obniz/obniz/libs/embeds/ble/ble_characteristic.py
obniz/obniz/libs/embeds/ble/ble_descriptor.py
obniz/obniz/libs/embeds/ble/ble_helper.py
obniz/obniz/libs/embeds/ble/ble_peripheral.py
obniz/obniz/libs/embeds/ble/ble_remote_attribute_abstract.py
obniz/obniz/libs/embeds/ble/ble_remote_characteristic.py
obniz/obniz/libs/embeds/ble/ble_remote_descriptor.py
obniz/obniz/libs/embeds/ble/ble_remote_peripheral.py
obniz/obniz/libs/embeds/ble/ble_remote_service.py
obniz/obniz/libs/embeds/ble/ble_scan.py
obniz/obniz/libs/embeds/ble/ble_security.py
obniz/obniz/libs/embeds/ble/ble_service.py
obniz/obniz/libs/hw/__init__.py
obniz/obniz/libs/hw/esp32w.json
obniz/obniz/libs/hw/index.py
obniz/obniz/libs/hw/obnizb1.json
obniz/obniz/libs/hw/obnizb2.json
obniz/obniz/libs/io_peripherals/__init__.py
obniz/obniz/libs/io_peripherals/ad.py
obniz/obniz/libs/io_peripherals/i2c.py
obniz/obniz/libs/io_peripherals/io.py
obniz/obniz/libs/io_peripherals/io_.py
obniz/obniz/libs/io_peripherals/pwm.py
obniz/obniz/libs/io_peripherals/spi.py
obniz/obniz/libs/io_peripherals/uart.py
obniz/obniz/libs/measurements/__init__.py
obniz/obniz/libs/measurements/logicanalyzer.py
obniz/obniz/libs/measurements/measure.py
obniz/obniz/libs/utils/__init__.py
obniz/obniz/libs/utils/util.py
obniz/parts/__init__.py
obniz/parts/Camera/__init__.py
obniz/parts/Camera/ArduCAMMini/README-ja.md
obniz/parts/Camera/ArduCAMMini/README.md
obniz-0.6.0.dist-info/LICENSE
obniz-0.6.0.dist-info/METADATA
obniz-0.6.0.dist-info/WHEEL
obniz-0.6.0.dist-info/top_level.txt
obniz-0.6.0.dist-info/RECORD
