Metadata-Version: 2.1
Name: obniz
Version: 0.6.0
Summary: obniz sdk for python
Home-page: https://obniz.io/
Author: yukisato
Author-email: yuki@yuki-sato.com
License: UNKNOWN
Platform: UNKNOWN
Classifier: Programming Language :: Python :: 3
Classifier: Programming Language :: Python :: 3.6
Classifier: Programming Language :: Python :: 3.7
Classifier: Operating System :: OS Independent
Requires-Dist: pyee (==6.0.0)
Requires-Dist: websockets (==7.0)
Requires-Dist: attrdict (==2.0.1)
Requires-Dist: semver (==2.8.1)
